MANIFEST.in
setup.cfg
setup.py
tracticketpost/__init__.py
tracticketpost/ticket.py
tracticketpost.egg-info/PKG-INFO
tracticketpost.egg-info/SOURCES.txt
tracticketpost.egg-info/dependency_links.txt
tracticketpost.egg-info/not-zip-safe
tracticketpost.egg-info/requires.txt
tracticketpost.egg-info/top_level.txt