Metadata-Version: 1.0
Name: tracticketpost
Version: 0.2a6dev
Summary: Submit new tickets to trac (via HTTP post)
Home-page: http://github.com/ralphbean/tracticketpost
Author: Ralph Bean
Author-email: ralph.bean@gmail.com
License: GPL
Platform: UNKNOWN
Classifier: Development Status :: 3 - Alpha
Classifier: Framework :: Trac
Classifier: Topic :: Software Development :: Libraries :: Python Modules
